EV/EV.py
EV/__init__.py
extinction_event-0.14.dist-info/METADATA
extinction_event-0.14.dist-info/RECORD
extinction_event-0.14.dist-info/WHEEL
extinction_event-0.14.dist-info/entry_points.txt
extinction_event-0.14.dist-info/top_level.txt
metaNODE/__init__.py
metaNODE/metaNODE.py
microDEX/__init__.py
microDEX/books-proof-of-concept.py
microDEX/microDEX.py
