Metadata-Version: 2.1
Name: extinction-event
Version: 0.14
Summary: Extinction event.Cryptocurrency algo trading tools.
Home-page: http://www.litepresence.com
Author: litepresence
Author-email: info@litepresence.com
License: UNKNOWN
Download-URL: https://github.com/litepresence/extinction-event/tarball/0.14
Keywords: bitshares,microDEX,extinction event
Platform: UNKNOWN
Classifier: Operating System :: OS Independent
Classifier: Programming Language :: Python :: 3
Classifier: Development Status :: 3 - Alpha
Classifier: Intended Audience :: Developers
Requires-Dist: scrypt
Requires-Dist: wheel
Requires-Dist: matplotlib
Requires-Dist: numpy
Requires-Dist: requests
Requires-Dist: bitshares (>=0.1.12)
Requires-Dist: uptick
